{
    "musescore3": "C:/Program Files/MuseScore 3/bin/MuseScore3.exe",
    "netbeans": "C:/Program Files/NetBeans-12.4/netbeans/bin/netbeans.exe",
    "whatsapp": "C:/Users/akosh/AppData/Local/WhatsApp/WhatsApp.exe",
    "spotify": "C:/Users/akosh/AppData/Local/Microsoft/WindowsApps/Spotify.exe",
    "steam": "C:/Program Files (x86)/Steam/Steam.exe",
    "messenger": "C:/Users/akosh/AppData/Local/Programs/Messenger/Messenger.exe",
    "musescore4": "C:/Program Files/MuseScore 4/bin/MuseScore4.exe",
    "skype": "C:/Program Files (x86)/Microsoft/Skype for Desktop/Skype.exe"
}
